pyqt_frameless_window/__init__.py
pyqt_frameless_window/framelessWindow.py
pyqt_frameless_window/base/__init__.py
pyqt_frameless_window/base/baseWidget.py
pyqt_frameless_window/linux/__init__.py
pyqt_frameless_window/linux/baseWidget.py
pyqt_frameless_window/linux/titleBar.py
pyqt_frameless_window/mac/__init__.py
pyqt_frameless_window/mac/baseWidget.py
pyqt_frameless_window/mac/titleBar.py
pyqt_frameless_window/windows/__init__.py
pyqt_frameless_window/windows/baseWidget.py
pyqt_frameless_window/windows/titleBar.py
pyqt_frameless_window/windows/src/__init__.py
pyqt_frameless_window/windows/src/c.py
pyqt_frameless_window/windows/src/win32utils.py
pyqt_frameless_window/windows/src/windowEffect.py
pyqt_frameless_window-0.0.85.dist-info/LICENSE
pyqt_frameless_window-0.0.85.dist-info/METADATA
pyqt_frameless_window-0.0.85.dist-info/WHEEL
pyqt_frameless_window-0.0.85.dist-info/top_level.txt
pyqt_frameless_window-0.0.85.dist-info/RECORD
