Metadata-Version: 2.1
Name: pyqt-frameless-window
Version: 0.0.85
Summary: PyQt(+PySide) Frameless Window
Home-page: https://github.com/yjg30737/pyqt-frameless-window.git
Author: Jung Gyu Yoon
Author-email: yjg30737@gmail.com
License: MIT
License-File: LICENSE
Requires-Dist: PyQt5
Requires-Dist: pywin32
Requires-Dist: qtpy
